script/AnDOviewer.py
script/__init__.py
script/_version.py
AnDOviewer-0.1.dist-info/METADATA
AnDOviewer-0.1.dist-info/WHEEL
AnDOviewer-0.1.dist-info/entry_points.txt
AnDOviewer-0.1.dist-info/top_level.txt
AnDOviewer-0.1.dist-info/RECORD
